{
  "date": "2026-07-21",
  "snapshots": [
    {
      "update_time": "2026年07月21日 09:30公表（日本時間）",
      "prices": {
        "GOLD": {
          "buy": "22890",
          "buy_diff": "+128",
          "retail": "23247",
          "retail_diff": "+129"
        },
        "PLATINUM": {
          "buy": "8930",
          "buy_diff": "-130",
          "retail": "9353",
          "retail_diff": "-130"
        },
        "SILVER": {
          "buy": "319.44",
          "buy_diff": "+3.96",
          "retail": "336.49",
          "retail_diff": "+3.96"
        }
      }
    }
  ]
}