{
  "update_time": "2025年12月02日 14:00公表（日本時間）",
  "prices": {
    "GOLD": {
      "retail": "23,284",
      "retail_diff": "-39",
      "buy": "23,093",
      "buy_diff": "-38",
      "retail_930diff": "-28",
      "buy_930diff": "-27"
    },
    "PLATINUM": {
      "retail": "9,126",
      "retail_diff": "-207",
      "buy": "8,907",
      "buy_diff": "-207",
      "retail_930diff": "-88",
      "buy_930diff": "-88"
    },
    "SILVER": {
      "retail": "316.80",
      "retail_diff": "+1.32",
      "buy": "306.35",
      "buy_diff": "+1.32",
      "retail_930diff": "-1.1",
      "buy_930diff": "-1.1"
    }
  }
}