{
  "update_time": "2025年12月25日 14:00公表（日本時間）",
  "prices": {
    "GOLD": {
      "retail": "24,763",
      "retail_diff": "-252",
      "buy": "24,571",
      "buy_diff": "-252",
      "retail_930diff": "+0",
      "buy_930diff": "+0"
    },
    "PLATINUM": {
      "retail": "11,897",
      "retail_diff": "-1,249",
      "buy": "11,678",
      "buy_diff": "-1,249",
      "retail_930diff": "-567",
      "buy_930diff": "-567"
    },
    "SILVER": {
      "retail": "408.10",
      "retail_diff": "+6.16",
      "buy": "397.65",
      "buy_diff": "+6.16",
      "retail_930diff": "+0",
      "buy_930diff": "+0"
    }
  }
}